pdfminer/__init__.py
pdfminer/arcfour.py
pdfminer/ascii85.py
pdfminer/cmapdb.py
pdfminer/converter.py
pdfminer/encodingdb.py
pdfminer/fontmetrics.py
pdfminer/glyphlist.py
pdfminer/latin_enc.py
pdfminer/layout.py
pdfminer/lzw.py
pdfminer/pdfcolor.py
pdfminer/pdfdevice.py
pdfminer/pdffont.py
pdfminer/pdfinterp.py
pdfminer/pdfparser.py
pdfminer/pdftypes.py
pdfminer/pslexer.py
pdfminer/psparser.py
pdfminer/rijndael.py
pdfminer/runlength.py
pdfminer/utils.py
pdfminer/cmap/__init__.py
pdfminer3k-1.3.3.dist-info/LICENSE.txt
pdfminer3k-1.3.3.dist-info/METADATA
pdfminer3k-1.3.3.dist-info/WHEEL
pdfminer3k-1.3.3.dist-info/top_level.txt
pdfminer3k-1.3.3.dist-info/RECORD
