Metadata-Version: 2.1
Name: pdfminer3k
Version: 1.3.3
Summary: Forked from original pdfminer
Home-page: https://github.com/canserhat77/pdfminer3k
Author: Serhat Can
Author-email: author@example.com
License: UNKNOWN
Download-URL: https://github.com/canserhat77/pdfminer3k/archive/v1.3.1.tar.gz
Platform: UNKNOWN
Classifier: Programming Language :: Python :: 3
Classifier: License :: OSI Approved :: MIT License
Classifier: Operating System :: OS Independent
Requires-Python: >=3.6
Requires-Dist: ply
